myapp/__init__.py
siblab-1.0.3.dist-info/METADATA
siblab-1.0.3.dist-info/WHEEL
siblab-1.0.3.dist-info/entry_points.txt
siblab-1.0.3.dist-info/top_level.txt
siblab-1.0.3.dist-info/RECORD
